nav/__init__.py
nav/__main__.py
nav/_metadata.py
nav/config.py
nav/constants.py
nav/exceptions.py
nav/plugins.py
nav/utils.py
nav/wrappers/json.py
nav-5.3.1.dist-info/LICENSE
nav-5.3.1.dist-info/METADATA
nav-5.3.1.dist-info/WHEEL
nav-5.3.1.dist-info/entry_points.txt
nav-5.3.1.dist-info/top_level.txt
nav-5.3.1.dist-info/RECORD
